cursive/__init__.py
cursive/assets/price/anthropic.py
cursive/assets/price/cohere.py
cursive/assets/price/openai.py
cursive/build_input.py
cursive/compat/pydantic.py
cursive/cursive.py
cursive/custom_function_call.py
cursive/function.py
cursive/hookable.py
cursive/model.py
cursive/pricing.py
cursive/stream.py
cursive/tests/test_function_compatibility.py
cursive/tests/test_function_schema.py
cursive/tests/test_setup.py
cursive/types.py
cursive/usage/anthropic.py
cursive/usage/cohere.py
cursive/usage/openai.py
cursive/utils.py
cursive/vendor/anthropic.py
cursive/vendor/cohere.py
cursive/vendor/index.py
cursive/vendor/openai.py
cursive/vendor/replicate.py
cursivepy-0.7.2.dist-info/METADATA
cursivepy-0.7.2.dist-info/WHEEL
cursivepy-0.7.2.dist-info/RECORD
