Metadata-Version: 2.1
Name: cursivepy
Version: 0.7.2
Summary: 
Author: Rodrigo Godinho
Author-email: god@meistrari.com
Requires-Python: >=3.10.0,<3.12
Classifier: Programming Language :: Python :: 3
Classifier: Programming Language :: Python :: 3.10
Classifier: Programming Language :: Python :: 3.11
Requires-Dist: anthropic (>=0.3.6,<0.4.0)
Requires-Dist: cohere (>=4.19.3,<5.0.0)
Requires-Dist: numpy (>=1.26.0,<2.0.0)
Requires-Dist: openai (>=0.27.8,<0.28.0)
Requires-Dist: pydantic (>=1,<3)
Requires-Dist: replicate (>=0.11.0,<0.12.0)
Requires-Dist: sorcery (>=0.2.2,<0.3.0)
Requires-Dist: tiktoken (>=0.4.0,<0.5.0)
Requires-Dist: tokenizers (>=0.13.3,<0.14.0)
